first_package/__init__.py
first_package/soma.py
first_package/subtracao.py
first_package_airton2junior-0.0.1.dist-info/METADATA
first_package_airton2junior-0.0.1.dist-info/WHEEL
first_package_airton2junior-0.0.1.dist-info/top_level.txt
first_package_airton2junior-0.0.1.dist-info/RECORD
