Metadata-Version: 2.1
Name: first_package_airton2junior
Version: 0.0.1
Summary: My first package
Home-page: https://github.com/Airton2Junior/FirstPackage.git
Author: AIRTON JUNIOR
Author-email: airton2junior@gmail.com
Requires-Python: >=3.8
